cbuae_mcp/__init__.py
cbuae_mcp/cli.py
cbuae_mcp/data.py
cbuae_mcp/pdf_processor.py
cbuae_mcp/semantic_search.py
cbuae_mcp/server.py
cbuae_mcp/web_scraper.py
cbuae_mcp-1.0.0.dist-info/licenses/LICENSE
cbuae_mcp-1.0.0.dist-info/METADATA
cbuae_mcp-1.0.0.dist-info/WHEEL
cbuae_mcp-1.0.0.dist-info/entry_points.txt
cbuae_mcp-1.0.0.dist-info/top_level.txt
cbuae_mcp-1.0.0.dist-info/RECORD
