Metadata-Version: 2.4
Name: cbuae-mcp
Version: 1.0.0
Summary: CBUAE Policy Agent - Model Context Protocol server for Central Bank of UAE policies and regulations
Author-email: CBUAE MCP Team <contact@example.com>
License: MIT
Project-URL: Homepage, https://github.com/cbuae-mcp/cbuae-mcp
Project-URL: Documentation, https://github.com/cbuae-mcp/cbuae-mcp#readme
Project-URL: Repository, https://github.com/cbuae-mcp/cbuae-mcp.git
Project-URL: Bug Tracker, https://github.com/cbuae-mcp/cbuae-mcp/issues
Keywords: mcp,cbuae,banking,regulations,fintech,uae,central-bank
Classifier: Development Status :: 4 - Beta
Classifier: Intended Audience :: Financial and Insurance Industry
Classifier: Intended Audience :: Developers
Classifier: License :: OSI Approved :: MIT License
Classifier: Operating System :: OS Independent
Classifier: Programming Language :: Python :: 3
Classifier: Programming Language :: Python :: 3.8
Classifier: Programming Language :: Python :: 3.9
Classifier: Programming Language :: Python :: 3.10
Classifier: Programming Language :: Python :: 3.11
Classifier: Programming Language :: Python :: 3.12
Classifier: Topic :: Office/Business :: Financial
Classifier: Topic :: Software Development :: Libraries :: Python Modules
Requires-Python: >=3.8
License-File: LICENSE
Requires-Dist: beautifulsoup4>=4.10.0
Requires-Dist: fastmcp>=2.10.1
Requires-Dist: fuzzywuzzy>=0.18.0
Requires-Dist: httpx>=0.24.0
Requires-Dist: mcp>=1.0.0
Requires-Dist: python-levenshtein>=0.12.0
Requires-Dist: sentence-transformers>=2.2.0
Requires-Dist: numpy>=1.21.0
Provides-Extra: dev
Requires-Dist: pytest>=7.0.0; extra == "dev"
Requires-Dist: pytest-asyncio>=0.21.0; extra == "dev"
Requires-Dist: black>=22.0.0; extra == "dev"
Requires-Dist: isort>=5.10.0; extra == "dev"
Requires-Dist: mypy>=1.0.0; extra == "dev"
Provides-Extra: pdf
Requires-Dist: pypdf2>=3.0.1; extra == "pdf"
Dynamic: license-file
